README.md
makeapt.py
setup.py
makeapt.egg-info/PKG-INFO
makeapt.egg-info/SOURCES.txt
makeapt.egg-info/dependency_links.txt
makeapt.egg-info/entry_points.txt
makeapt.egg-info/requires.txt
makeapt.egg-info/top_level.txt